pytest_yaml_yoyo/__init__.py
pytest_yaml_yoyo/create_funtion.py
pytest_yaml_yoyo/db.py
pytest_yaml_yoyo/exceptions.py
pytest_yaml_yoyo/extract.py
pytest_yaml_yoyo/http_session.py
pytest_yaml_yoyo/log.py
pytest_yaml_yoyo/my_builtins.py
pytest_yaml_yoyo/parser.py
pytest_yaml_yoyo/plugin.py
pytest_yaml_yoyo/render_template_obj.py
pytest_yaml_yoyo/report_notify.py
pytest_yaml_yoyo/request_session.py
pytest_yaml_yoyo/runner.py
pytest_yaml_yoyo/start_project.py
pytest_yaml_yoyo/swagger_parser.py
pytest_yaml_yoyo/validate.py
pytest_yaml_yoyo-1.2.7.dist-info/METADATA
pytest_yaml_yoyo-1.2.7.dist-info/WHEEL
pytest_yaml_yoyo-1.2.7.dist-info/entry_points.txt
pytest_yaml_yoyo-1.2.7.dist-info/top_level.txt
pytest_yaml_yoyo-1.2.7.dist-info/RECORD
