Metadata-Version: 2.1
Name: pytest-yaml-yoyo
Version: 1.2.7
Summary: http/https API run by yaml
Home-page: https://github.com/yoyoketang/pytest-yaml-yoyo
Author: 上海-悠悠
Author-email: 283340479@qq.com
License: proprietary
Keywords: pytest,py.test,pytest-yaml,pytest-yaml-yoyo
Classifier: Framework :: Pytest
Classifier: Programming Language :: Python
Classifier: Topic :: Software Development :: Testing
Classifier: Programming Language :: Python :: 3.8
Requires-Python: >=3.8
Requires-Dist: Jinja2 (>=3.1.2)
Requires-Dist: jmespath (>=0.9.5)
Requires-Dist: jsonpath (>=0.82)
Requires-Dist: pytest (>=7.2.0)
Requires-Dist: PyYAML (>=6.0)
Requires-Dist: requests (>=2.28.1)
Requires-Dist: allure-pytest (>=2.12.0)
Requires-Dist: pymysql (>=1.0.2)
Requires-Dist: DingtalkChatbot (>=1.5.7)
Requires-Dist: Faker (>=15.3.4)
Requires-Dist: requests-toolbelt (>=0.10.1)
